MANIFEST.in
setup.py
lib/ansible/__init__.py
lib/ansible/module_utils/__init__.py
lib/ansible/module_utils/alicloud_ecs.py
lib/ansible/module_utils/alicloud_oss.py
lib/ansible/modules/__init__.py
lib/ansible/modules/setup.py
lib/ansible/modules/cloud/__init__.py
lib/ansible/modules/cloud/alicloud/__init__.py
lib/ansible/modules/cloud/alicloud/alicloud_bucket.py
lib/ansible/modules/cloud/alicloud/alicloud_bucket_object.py
lib/ansible/modules/cloud/alicloud/alicloud_disk.py
lib/ansible/modules/cloud/alicloud/alicloud_instance.py
lib/ansible/modules/cloud/alicloud/alicloud_instance_facts.py
lib/ansible/modules/cloud/alicloud/alicloud_route_entry.py
lib/ansible/modules/cloud/alicloud/alicloud_security_group.py
lib/ansible/modules/cloud/alicloud/alicloud_slb_lb.py
lib/ansible/modules/cloud/alicloud/alicloud_slb_listener.py
lib/ansible/modules/cloud/alicloud/alicloud_slb_server.py
lib/ansible/modules/cloud/alicloud/alicloud_slb_vsg.py
lib/ansible/modules/cloud/alicloud/alicloud_vpc.py
lib/ansible/modules/cloud/alicloud/alicloud_vswitch.py
lib/ansible/modules/cloud/alicloud/ecs_ami.py
lib/ansible/modules/cloud/alicloud/ecs_eip.py
lib/ansible/modules/cloud/alicloud/ecs_slb_lb.py
lib/ansible/modules/cloud/alicloud/ecs_slb_vsg.py
lib/ansible/modules/cloud/alicloud/oss.py
lib/ansible/modules/cloud/alicloud/rds.py
lib/ansible/modules/cloud/alicloud/rds_account.py
lib/ansible/modules/cloud/alicloud/ros.py
lib/ansible/utils/__init__.py
lib/ansible/utils/module_docs_fragments/__init__.py
lib/ansible/utils/module_docs_fragments/alicloud.py
lib/ansible_alicloud_bak.egg-info/PKG-INFO
lib/ansible_alicloud_bak.egg-info/SOURCES.txt
lib/ansible_alicloud_bak.egg-info/dependency_links.txt
lib/ansible_alicloud_bak.egg-info/requires.txt
lib/ansible_alicloud_bak.egg-info/top_level.txt