Metadata-Version: 1.1
Name: ansible-alicloud-bak
Version: 1.0.9
Summary: Ansible provider for Alicloud.
Home-page: https://github.com/alibaba/ansible-provider/tree/master/lib/ansible
Author: xiaozhu
Author-email: heguimin36@163.com
License: MIT
Platform: UNKNOWN
Classifier: Development Status :: 3 - Alpha
Classifier: Intended Audience :: Developers
Classifier: Topic :: Software Development :: Build Tools
Classifier: License :: OSI Approved :: MIT License
Classifier: Programming Language :: Python :: 2
Classifier: Programming Language :: Python :: 2.6
Classifier: Programming Language :: Python :: 2.7
